{
  "epsilon": [
    0.0
  ],
  "epsilon_T": [
    2000085
  ],
  "test_battle_won_mean": [
    0.0
  ],
  "test_battle_won_mean_T": [
    2000085
  ],
  "test_dead_allies_mean": [
    8.0
  ],
  "test_dead_allies_mean_T": [
    2000085
  ],
  "test_dead_enemies_mean": [
    7.0
  ],
  "test_dead_enemies_mean_T": [
    2000085
  ],
  "test_ep_length_mean": [
    68.0
  ],
  "test_ep_length_mean_T": [
    2000085
  ],
  "test_return_mean": [
    15.556886227544911
  ],
  "test_return_mean_T": [
    2000085
  ],
  "test_return_std": [
    0.0
  ],
  "test_return_std_T": [
    2000085
  ]
}